{
    "find_int_roots.py": [
        {
            "operation": "PASTE",
            "lines": 6,
            "keyStrokeTimeStamp": "Tue Jul 20 2021 14:15:12",
            "keyStrokeInfo": "import cmath\r\ndef fun_find_int_roots(a, b, c):\r\n    d=(b**2)-(4*a*c)\r\n    sol1=(-b-(cmath.sqrt(d)))/2*a\r\n    sol2=(-b+(cmath.sqrt(d)))/2*a\r\n    return sol1,sol2",
            "position": "12,1"
        },
        {
            "operation": "DELETE",
            "lines": 3,
            "keyStrokeTimeStamp": "Tue Jul 20 2021 14:15:16",
            "keyStrokeInfo": "",
            "position": "8,1"
        }
    ]
}